llm_bedrock.py
llm_bedrock-0.4.dist-info/LICENSE
llm_bedrock-0.4.dist-info/METADATA
llm_bedrock-0.4.dist-info/WHEEL
llm_bedrock-0.4.dist-info/entry_points.txt
llm_bedrock-0.4.dist-info/top_level.txt
llm_bedrock-0.4.dist-info/RECORD
