Metadata-Version: 2.1
Name: llm-bedrock
Version: 0.4
Summary: Run prompts against models hosted on AWS Bedrock
Author: Simon Willison
License: Apache-2.0
Project-URL: Homepage, https://github.com/simonw/llm-bedrock
Project-URL: Changelog, https://github.com/simonw/llm-bedrock/releases
Project-URL: Issues, https://github.com/simonw/llm-bedrock/issues
Project-URL: CI, https://github.com/simonw/llm-bedrock/actions
Classifier: License :: OSI Approved :: Apache Software License
Requires-Python: >=3.9
License-File: LICENSE
Requires-Dist: llm>=0.19
Requires-Dist: boto3>=1.35.74
Provides-Extra: test
Requires-Dist: pytest; extra == "test"
Requires-Dist: pytest-recording; extra == "test"
